pytest_qgis/__init__.py
pytest_qgis/_version.py
pytest_qgis/mock_qgis_classes.py
pytest_qgis/py.typed
pytest_qgis/pytest_qgis.py
pytest_qgis/qgis_bot.py
pytest_qgis/qgis_interface.py
pytest_qgis/utils.py
pytest_qgis-2.1.0.dist-info/LICENSE
pytest_qgis-2.1.0.dist-info/METADATA
pytest_qgis-2.1.0.dist-info/WHEEL
pytest_qgis-2.1.0.dist-info/entry_points.txt
pytest_qgis-2.1.0.dist-info/top_level.txt
pytest_qgis-2.1.0.dist-info/RECORD
