Metadata-Version: 2.1
Name: pytest-qgis
Version: 2.1.0
Summary: A pytest plugin for testing QGIS python plugins
Author-email: "Gispo Ltd." <info@gispo.fi>
Maintainer-email: "Gispo Ltd." <info@gispo.fi>
License: GNU GENERAL PUBLIC LICENSE
Project-URL: homepage, https://github.com/GispoCoding/pytest-qgis
Project-URL: repository, https://github.com/GispoCoding/pytest-qgis
Project-URL: changelog, https://github.com/GispoCoding/pytest-qgis/CHANGELOG.md
Keywords: pytest,qgis,QGIS,PyQGIS
Classifier: Development Status :: 5 - Production/Stable
Classifier: Framework :: Pytest
Classifier: Intended Audience :: Developers
Classifier: Topic :: Software Development :: Testing
Classifier: Programming Language :: Python
Classifier: Programming Language :: Python :: 3
Classifier: Programming Language :: Python :: 3.7
Classifier: Programming Language :: Python :: 3.8
Classifier: Programming Language :: Python :: 3.9
Classifier: Programming Language :: Python :: 3.10
Classifier: Programming Language :: Python :: 3.11
Classifier: Programming Language :: Python :: 3 :: Only
Classifier: Programming Language :: Python :: Implementation :: CPython
Classifier: Programming Language :: Python :: Implementation :: PyPy
Classifier: Operating System :: OS Independent
Classifier: License :: OSI Approved :: GNU General Public License v2 (GPLv2)
Requires-Python: >=3.7
License-File: LICENSE
Requires-Dist: pytest >=6.0
